setup.py
QmongoHelper/__db.py
QmongoHelper/__init__.py
qmongohelper.egg-info/PKG-INFO
qmongohelper.egg-info/SOURCES.txt
qmongohelper.egg-info/dependency_links.txt
qmongohelper.egg-info/not-zip-safe
qmongohelper.egg-info/requires.txt
qmongohelper.egg-info/top_level.txt