Metadata-Version: 1.0
Name: qmongohelper
Version: 0.1
Summary: a simple way to use mongo db, let db like dict
Home-page: https://github.com/Qingluan/QmongoHelper.git
Author: Qing luan
Author-email: darkhackdevil@gmail.com
License: MIT
Platform: UNKNOWN
